raytools/__init__.py
raytools/cli.py
raytools/imagetools.py
raytools/io.py
raytools/translate.py
raytools/utility.py
raytools/cal/rayinit.cal
raytools/evaluate/__init__.py
raytools/evaluate/basemetricset.py
raytools/evaluate/colormetricset.py
raytools/evaluate/hvsgsm.py
raytools/evaluate/metricset.py
raytools/evaluate/positionindex.py
raytools/evaluate/retina.py
raytools/mapper/__init__.py
raytools/mapper/angularmixin.py
raytools/mapper/mapper.py
raytools/mapper/perspectiveviewmapper.py
raytools/mapper/solidviewmapper.py
raytools/mapper/viewmapper.py
raytools-0.1.8.dist-info/licenses/LICENSE
raytools-0.1.8.dist-info/METADATA
raytools-0.1.8.dist-info/WHEEL
raytools-0.1.8.dist-info/entry_points.txt
raytools-0.1.8.dist-info/top_level.txt
raytools-0.1.8.dist-info/RECORD
