Metadata-Version: 2.4
Name: raytools
Version: 0.1.8
Summary: working with hdr images, numpy and coordinate transformations for lighting simulation
Home-page: https://github.com/stephanwaz/raytools
Author: Stephen Wasilewski
Author-email: stephanwaz@gmail.com
License: Mozilla Public License 2.0 (MPL 2.0)
Keywords: raytools
Classifier: Development Status :: 2 - Pre-Alpha
Classifier: License :: OSI Approved :: Mozilla Public License 2.0 (MPL 2.0)
Classifier: Natural Language :: English
Classifier: Programming Language :: Python :: 3.7
Classifier: Programming Language :: Python :: 3.8
Classifier: Programming Language :: Python :: 3.9
Classifier: Programming Language :: Python :: 3.10
Requires-Python: >=3.6.8
License-File: LICENSE
Requires-Dist: clasp
Requires-Dist: numpy
Requires-Dist: scipy
Requires-Dist: tqdm
Dynamic: author
Dynamic: author-email
Dynamic: classifier
Dynamic: description
Dynamic: home-page
Dynamic: keywords
Dynamic: license
Dynamic: license-file
Dynamic: requires-dist
Dynamic: requires-python
Dynamic: summary
